Metadata-Version: 2.1
Name: positional-vectorizer
Version: 0.0.9
Summary: Positional Vectorizer is a scikit-learn transformer that converts text to bag of words vector using a positional ranking algorithm as score
Home-page: https://github.com/timotta/positional-vectorizer
Author: Tiago Albineli Motta
Author-email: timotta@gmail.com
License: new BSD
Keywords: machine learning,embedding,vectorizer,scikit-learn,text,NLP
Requires-Python: >=3.10, <3.12
License-File: LICENSE
Requires-Dist: scikit-learn>=1.4.2
Requires-Dist: typing-extensions>=4.11.0
